Workbook

Sheet Fiche Client
B6: Client
B7: Secteur
B8: Nombre de ligne de production
B9: Nombre de machine
B10: Nombre de poste manuel

Sheet Gestion Exigences
B2: Gestion Exigences Projet | N2: Chiffrage Réalisation (SF only) | Q2: Revue et Vérification Pendant la Conception
B4: BU | G4: SF
B5: Client | D5: APEM
B6: Projet | D6: Digitalisation Stand Up Meeting
B8: Réf Modèle Document | D8: MD203 | I8: Confidentiel | Usage Client Limité
B9: Version Modèle Document | D9: V1.5
B11: ID | C11: Exigence | D11: Nature | E11: Catégorie | F11: Exigence idenfiée pendant la phase | G11: Description de l'exigence | H11: Source | I11: Desciption de la solution MOMSOFT | J11: Ecart | K11: Validation Interne | L11: Validation Interne par: | M11: Statut Client | N11: HJ Dev | O11: HJ Analyse et Test | P11: Total HJ | Q11: Description comment la conception de la solution prend en compte l'exigence client | R11: Conception réalisée par: | S11: Revue conception réalisée par | T11: Vérification de la conception réalisée par | U11: Preuve de vérification | V11: Notes
B12: E001 | C12: Configuration des données | D12: Fonctionnelle | E12: SF-Fonctionnelle | F12: Commerciale | G12: Configurer les donnnées nécessaires de l'usine | H12: Workshop/réunion client | I12: La solution comprend un Module Core permettant la modélisation, la gestion et la planification d'une usine connectée : •Modélisation hiérarchique de l’usine : Sites, ateliers, lignes de production, stations, machines •Gestion des produits •Gestion des incidents et des défauts •Gestion des utilisateurs et des autorisations : Rôles et accès contrôlés •Gestion des équipes •Planification des lignes et des équipes | K12: Validée | L12: Mahdi B. | N12: 0 | O12: =Tableau3[[#This Row],[HJ Dev]]*(25%+25%) -> 0 | P12: =Tableau3[[#This Row],[HJ Analyse et Test]]+Tableau3[[#This Row],[HJ Dev]] -> 0 | Q12: N/A | R12: N/A | S12: N/A | T12: N/A | U12: N/A
B13: E002 | C13: Importation des données | D13: Fonctionnelle | E13: SF-Fonctionnelle | F13: Commerciale | G13: Automatiser la configuration des données | H13: Workshop/réunion client | I13: la solution intègre un Module d’Intégration SI pour l’automatisation des échanges de données, incluant : •Importation automatique de données à partir de fichiers CSV ou des systèmes d’information clients •Intégration des principales entités : Produits, utilisateurs, outillages •Gestion détaillée des erreurs pour une intégration fluide | K13: Validée | L13: Mahdi B. | N13: 0 | O13: =Tableau3[[#This Row],[HJ Dev]]*(25%+25%) -> 0 | P13: =Tableau3[[#This Row],[HJ Analyse et Test]]+Tableau3[[#This Row],[HJ Dev]] -> 0
B14: E003 | C14: Pilotage de l'îlot : Suivi de la performance | D14: Fonctionnelle | E14: SF-Fonctionnelle | F14: Commerciale | G14: Digitaliser la partie Suivi de la performance du tableau de bord Pilotage de l'ilot. | H14: Workshop/réunion client | I14: Suivi de la Performance Ajouter un graphique de suivi de la performance affichant le nombre d'heures réalisées par rapport à l'objectif horaire | K14: Validée | L14: Mahdi B. | N14: 0 | O14: =Tableau3[[#This Row],[HJ Dev]]*(25%+25%) -> 0 | P14: =Tableau3[[#This Row],[HJ Analyse et Test]]+Tableau3[[#This Row],[HJ Dev]] -> 0
B15: E004 | C15: Pilotage de l'îlot : Suivi 5S | D15: Fonctionnelle | E15: SF-Fonctionnelle | F15: Commerciale | G15: Digitaliser la partie Suivi 5S du tableau de bord Pilotage de l'ilot. | H15: Workshop/réunion client | I15: Tableau de Bord 5S •Ajouter la possibilité de charger et afficher des images dans le tableau de bord 5S pour intégrer les standards des îlots •Afficher le score 5S hebdomadaire par atelier •Créer, mettre à jour et suivre les actions issues des évaluations 5S | K15: Validée | L15: Mahdi B. | N15: 0 | O15: =Tableau3[[#This Row],[HJ Dev]]*(25%+25%) -> 0 | P15: =Tableau3[[#This Row],[HJ Analyse et Test]]+Tableau3[[#This Row],[HJ Dev]] -> 0
B16: E005 | C16: Pilotage de l'îlot : Suivi QRQC | D16: Fonctionnelle | E16: SF-Fonctionnelle | F16: Commerciale | G16: Digitaliser la partie Suivi QRQC du tableau de bord Pilotage de l'ilot. | H16: Workshop/réunion client | I16: Tableau de Bord QRQC (Quick Response Quality Control) •Afficher le nombre de QRQC (ouverts, en cours, traités, etc.) •Présenter le nombre de QRQC par niveau de criticité •Offrir un accès rapide aux fiches QRQC depuis le tableau de bord •Créer, mettre à jour et suivre les actions issues des QRQC | K16: Validée | L16: Mahdi B. | N16: 0 | O16: =Tableau3[[#This Row],[HJ Dev]]*(25%+25%) -> 0 | P16: =Tableau3[[#This Row],[HJ Analyse et Test]]+Tableau3[[#This Row],[HJ Dev]] -> 0
B17: E006 | C17: Pilotage de l'îlot : Tour de terrain | D17: Fonctionnelle | E17: SF-Fonctionnelle | F17: Commerciale | G17: Digitaliser la partie Tour du terrain du tableau de bord Pilotage de l'ilot. | H17: Workshop/réunion client | I17: Checklist et Suivi Gemba Walk •Ajouter une checklist Gemba Walk •Afficher des statistiques basées sur la checklist •Mettre en place un tableau de bord des postes de production et de leur statut (Contrôlé, À contrôler) •Créer, mettre à jour et suivre les actions issues des évaluations Gemba Walk | K17: Validée | L17: Mahdi B. | N17: 0 | O17: =Tableau3[[#This Row],[HJ Dev]]*(25%+25%) -> 0 | P17: =Tableau3[[#This Row],[HJ Analyse et Test]]+Tableau3[[#This Row],[HJ Dev]] -> 0
B18: E007 | C18: Suivi d'activité : KPI du mois | D18: Fonctionnelle | E18: SF-Fonctionnelle | F18: Commerciale | G18: Digitaliser la partie KPI du mois du tableau de bord Suivi de l'activité. | H18: Workshop/réunion client | I18: Tableaux de Bord KPI : Sécurité, Environnement, Qualité et OTD Ajouter un graphique Sécurité/Environnement dans la section KPI mensuelle : •Présente le nombre d’accidents avec arrêt (APEM TN) et les incidents environnementaux (SACEMA) dans toutes les usines du groupe •Données issues du système ERP Ajouter un graphique de Performance Qualité : •Affiche le PPM mensuel vs. l’objectif PPM vs. la moyenne PPM sur 12 mois glissants •Données issues du système ERP Ajouter un graphique de suivi OTD (On-Time Delivery) : •Les dates de fin planifiées sont extraites d’un fichier Excel chargé chaque semaine •Les dates de fin réelles sont issues du système ERP Afficher la Marge sur coût direct et les Ventes Sacema, avec des données issues de l’ERP | K18: Validée | L18: Mahdi B. | N18: 0 | O18: =Tableau3[[#This Row],[HJ Dev]]*(25%+25%) -> 0 | P18: =Tableau3[[#This Row],[HJ Analyse et Test]]+Tableau3[[#This Row],[HJ Dev]] -> 0
B19: E008 | C19: Suivi d'activité : KPI de la semaine | D19: Fonctionnelle | E19: SF-Fonctionnelle | F19: Commerciale | G19: Digitaliser la partie KPI de la semaine | H19: Workshop/réunion client | I19: Ajouter le graphique Nombre d'incidents sécurité et environnement : données saisies manuellement Ajouter le graphique Nombre d'OF refusé ; données saisies manuellement. Ajouter le graphique Taux de respect engagement : OTD : OF clôturé à l'heure / OF Planifé. Ajouter le graphique Nombre d'heure non productivres : Données saisies manuellement. | K19: Validée | L19: Mahdi B. | N19: 0 | O19: =Tableau3[[#This Row],[HJ Dev]]*(25%+25%) -> 0 | P19: =Tableau3[[#This Row],[HJ Analyse et Test]]+Tableau3[[#This Row],[HJ Dev]] -> 0
B20: E009 | C20: Gestion de tâches | D20: Fonctionnelle | E20: SF-Fonctionnelle | F20: Commerciale | G20: Digitaliser la gestion des tâches | H20: Workshop/réunion client | I20: Gestion des Tâches (Adaptation du Module Standard de Smart Factory) Ajouts et modifications : •Ajouter un type de tâche "Suggestion d’amélioration" •Ajouter "Réclamation client" comme source de tâche •Limiter la planification des tâches à 2 semaines pour les tâches de priorité haute et moyenne •Une tâche ne peut être reportée qu’une seule fois après sa création | K20: Validée | L20: Mahdi B. | N20: 0 | O20: =Tableau3[[#This Row],[HJ Dev]]*(25%+25%) -> 0 | P20: =Tableau3[[#This Row],[HJ Analyse et Test]]+Tableau3[[#This Row],[HJ Dev]] -> 0
B21: E010 | C21: Instructions de travail | D21: Fonctionnelle | E21: SF-Fonctionnelle | F21: Commerciale | G21: Permettre d'afficher des instructions de travail au niveau du Tableau de bord | H21: Workshop/réunion client | I21: Intégration des Instructions de Travail Permettre la sélection et l’affichage d’un fichier depuis le module Instructions de Travail dans le tableau de bord | K21: Validée | L21: Mahdi B. | N21: 3 | O21: =Tableau3[[#This Row],[HJ Dev]]*(25%+25%) -> 1.5 | P21: =Tableau3[[#This Row],[HJ Analyse et Test]]+Tableau3[[#This Row],[HJ Dev]] -> 4.5
I22: Ajouter le groupe d'indicateur Sécurité et Environnement | N22: 1.5 | O22: =Tableau3[[#This Row],[HJ Dev]]*0.5 -> 0.75 | P22: =Tableau3[[#This Row],[HJ Analyse et Test]]+Tableau3[[#This Row],[HJ Dev]] -> 2.25
I23: Méthode standard Chargement Excel | J23: Fichier Standard SF | N23: 3 | O23: =Tableau3[[#This Row],[HJ Dev]]*0.5 -> 1.5 | P23: =Tableau3[[#This Row],[HJ Analyse et Test]]+Tableau3[[#This Row],[HJ Dev]] -> 4.5
I24: Chargement des données à partir de l'ERP par webservice : A l'appui d'un bouton ou automatiquement selon une fréquence | N24: 4 | O24: =Tableau3[[#This Row],[HJ Dev]]*0.5 -> 2 | P24: =Tableau3[[#This Row],[HJ Analyse et Test]]+Tableau3[[#This Row],[HJ Dev]] -> 6 | V24: avec nouveau service
I25: Ajouter le groupe d'indicateur Quality performance PPM | N25: 1 | O25: =Tableau3[[#This Row],[HJ Dev]]*0.5 -> 0.5 | P25: =Tableau3[[#This Row],[HJ Analyse et Test]]+Tableau3[[#This Row],[HJ Dev]] -> 1.5
I26: Ajouter le groupe d'indicateur Delays du groupe | N26: 1 | O26: =Tableau3[[#This Row],[HJ Dev]]*0.5 -> 0.5 | P26: =Tableau3[[#This Row],[HJ Analyse et Test]]+Tableau3[[#This Row],[HJ Dev]] -> 1.5 | V26: Avec traitement fichier Excel date fin planifié et Webservice Date fin réelle
I27: Ajouter le groupe d'indicateur Costs | N27: 2 | O27: =Tableau3[[#This Row],[HJ Dev]]*0.5 -> 1 | P27: =Tableau3[[#This Row],[HJ Analyse et Test]]+Tableau3[[#This Row],[HJ Dev]] -> 3
I28: Paramètrage de l'affichage des indicateurs groupes | N28: 0.5 | O28: =Tableau3[[#This Row],[HJ Dev]]*0.5 -> 0.25 | P28: =Tableau3[[#This Row],[HJ Analyse et Test]]+Tableau3[[#This Row],[HJ Dev]] -> 0.75
I29: Ajouter le bloc d'indicateur Production tracking | N29: 2.5 | O29: =Tableau3[[#This Row],[HJ Dev]]*0.5 -> 1.25 | P29: =Tableau3[[#This Row],[HJ Analyse et Test]]+Tableau3[[#This Row],[HJ Dev]] -> 3.75
I30: Ajouter le groupe d'indicateur Delays | N30: 3 | O30: =Tableau3[[#This Row],[HJ Dev]]*0.5 -> 1.5 | P30: =Tableau3[[#This Row],[HJ Analyse et Test]]+Tableau3[[#This Row],[HJ Dev]] -> 4.5
I31: Ajouter le groupe d'indicateur 6s | N31: 3 | O31: =Tableau3[[#This Row],[HJ Dev]]*0.5 -> 1.5 | P31: =Tableau3[[#This Row],[HJ Analyse et Test]]+Tableau3[[#This Row],[HJ Dev]] -> 4.5
I32: Ajouter le groupe d'indicateur QRQC | N32: 4 | O32: =Tableau3[[#This Row],[HJ Dev]]*0.5 -> 2 | P32: =Tableau3[[#This Row],[HJ Analyse et Test]]+Tableau3[[#This Row],[HJ Dev]] -> 6
I33: Ajouter le groupe d'indicateur Gemba Walk | N33: 3 | O33: =Tableau3[[#This Row],[HJ Dev]]*0.5 -> 1.5 | P33: =Tableau3[[#This Row],[HJ Analyse et Test]]+Tableau3[[#This Row],[HJ Dev]] -> 4.5
I34: Adapter le groupe d'indicateur Sécurité et Environnement | N34: 1.5 | O34: =Tableau3[[#This Row],[HJ Dev]]*0.5 -> 0.75 | P34: =Tableau3[[#This Row],[HJ Analyse et Test]]+Tableau3[[#This Row],[HJ Dev]] -> 2.25
I35: Adapter le groupe Quality | N35: 3 | O35: =Tableau3[[#This Row],[HJ Dev]]*0.5 -> 1.5 | P35: =Tableau3[[#This Row],[HJ Analyse et Test]]+Tableau3[[#This Row],[HJ Dev]] -> 4.5
I36: Adapter le groupe Cost | N36: 2 | O36: =Tableau3[[#This Row],[HJ Dev]]*0.5 -> 1 | P36: =Tableau3[[#This Row],[HJ Analyse et Test]]+Tableau3[[#This Row],[HJ Dev]] -> 3
I37: Configuration des Vues par Entités | N37: 2 | O37: =Tableau3[[#This Row],[HJ Dev]]*0.5 -> 1 | P37: =Tableau3[[#This Row],[HJ Analyse et Test]]+Tableau3[[#This Row],[HJ Dev]] -> 3
I38: Configuration de la période de filtrage par défaut | N38: 3 | O38: =Tableau3[[#This Row],[HJ Dev]]*0.5 -> 1.5 | P38: =Tableau3[[#This Row],[HJ Analyse et Test]]+Tableau3[[#This Row],[HJ Dev]] -> 4.5
N39: =SUBTOTAL(109,Tableau3[HJ Dev]) -> 43 | P39: =SUBTOTAL(109,Tableau3[Total HJ]) -> 64.5
P44: =SUM(P21:P38) -> 64.5

Sheet Modifs Doc
B3: Gestion Exigences Projet
B5: ='Gestion Exigences'!B5 -> Client | D5: ='Gestion Exigences'!#REF! -> #REF!
B6: ='Gestion Exigences'!B6 -> Projet | D6: ='Gestion Exigences'!#REF! -> #REF!
B7: ='Gestion Exigences'!#REF! -> #REF! | D7: ='Gestion Exigences'!#REF! -> #REF!
B8: ='Gestion Exigences'!#REF! -> #REF! | D8: ='Gestion Exigences'!#REF! -> #REF!
B10: ='Gestion Exigences'!B8 -> Réf Modèle Document | C10: ='Gestion Exigences'!D8 -> MD203
B11: ='Gestion Exigences'!B9 -> Version Modèle Document | C11: ='Gestion Exigences'!D9 -> V1.5
B13: Version | C13: Date | D13: Modifications | E13: Auteur(s) | F13: Vérificateur(s) | G13: Approbateur
B14: V1.0 | C14: 45342 | D14: Version initiale | E14: Nihel K. | F14: Mahdi B. + Ferjania BA | G14: Imed A.
B15: V1.1 | C15: 45701 | D15: Adaptation des paramètres et du logo | E15: Moatez D. | F15: Mahdi B. | G15: Imed A.

Sheet Params
B2: BU | C2: Nature | D2: Exigence identifiée pendant la phase | E2: Source | F2: Oui/Non | G2: Statut Client | H2: Statut Interne | I2: Catégorie
B3: SF | C3: Fonctionnelle | D3: Commerciale | E3: CdC client | F3: Oui | G3: Validée par le client | H3: Validée | I3: *** SF
B4: R&D | C4: Performance | D4: Conception | E4: Workshop/réunion client | F4: Non | G4: Non validée par client | H4: Non validée | I4: SF-Processus
B5: A définir | C5: Reglementaire | D5: Réalisation | E5: Workshop/réunion Interne | F5: N/A | G5: N/A | H5: N/A | I5: SF-Fonctionnelle
B6: A définir | C6: Sécurité | D6: Mise en œuvre | E6: Standards client | I6: SF-Connectivité Machine
C7: Standard Client | D7: Support et maintenance | E7: Standards MOMSOFT | I7: SF-Intégration SI
C8: Standard MOMSOFT | E8: Reglementation | I8: SF-Software
E9: Demande modification | I9: SF-Infra IT
I11: *** TC
I12: TC-Prestations sur site client
